.gitignore
LICENSE
MANIFEST.in
README.rst
setup.py
mezzanine_recipes/.DS_Store
mezzanine_recipes/__init__.py
mezzanine_recipes/__init__.pyc
mezzanine_recipes/admin.py
mezzanine_recipes/api.py
mezzanine_recipes/defaults.py
mezzanine_recipes/fields.py
mezzanine_recipes/forms.py
mezzanine_recipes/models.py
mezzanine_recipes/tests.py
mezzanine_recipes/urls.py
mezzanine_recipes/views.py
mezzanine_recipes.egg-info/PKG-INFO
mezzanine_recipes.egg-info/SOURCES.txt
mezzanine_recipes.egg-info/dependency_links.txt
mezzanine_recipes.egg-info/not-zip-safe
mezzanine_recipes.egg-info/requires.txt
mezzanine_recipes.egg-info/top_level.txt
mezzanine_recipes/fixtures/mezzanine_required.json
mezzanine_recipes/locale/de/LC_MESSAGES/django.mo
mezzanine_recipes/locale/de/LC_MESSAGES/django.po
mezzanine_recipes/migrations/0001_initial.py
mezzanine_recipes/migrations/__init__.py
mezzanine_recipes/templates/admin/includes/quick_blog.html
mezzanine_recipes/templates/blog/blog_post_detail.html
mezzanine_recipes/templates/recipe/recipe_detail.html
mezzanine_recipes/templates/recipe/recipe_list.html
mezzanine_recipes/templatetags/__init__.py
mezzanine_recipes/templatetags/blog_tags.py
mezzanine_recipes/templatetags/twitter_tags.py